flaskbp/__init__.py
flaskbp/boilerplate.py
flaskbp/generate.py
flaskbp/files/app.py
flaskbp/files/index.html
flaskbp/files/jquery.min.js
flaskbp/files/main.js
flaskbp/files/styles.css
flaskbp/files/sweetalert.min.js
flaskbp/files/utils.js
flaskbp-0.3.dist-info/METADATA
flaskbp-0.3.dist-info/WHEEL
flaskbp-0.3.dist-info/entry_points.txt
flaskbp-0.3.dist-info/top_level.txt
flaskbp-0.3.dist-info/RECORD
