Metadata-Version: 2.1
Name: flaskbp
Version: 0.3
Summary: A python package for basic Flask app boilerplate.
Home-page: https://github.com/frankhart2018/flaskbp
Author: Siddhartha Dhar Choudhury
Author-email: sdharchou@gmail.com
License: GNU General Public License v3
Platform: UNKNOWN
Classifier: License :: OSI Approved :: GNU General Public License v3 (GPLv3)
Classifier: Programming Language :: Python :: 3
Classifier: Programming Language :: Python :: 3.9
Classifier: Programming Language :: Python :: 3.8
Classifier: Programming Language :: Python :: 3.7
Classifier: Programming Language :: Python :: 3.6
